pyramage/__init__.py
pyramage-1.0.0.dist-info/METADATA
pyramage-1.0.0.dist-info/WHEEL
pyramage-1.0.0.dist-info/top_level.txt
pyramage-1.0.0.dist-info/RECORD
