Metadata-Version: 2.1
Name: pyramage
Version: 1.0.0
Summary: Python random image generator built using perlin noise algorithm
Home-page: https://github.com/sreedevk/pyramage.git
Author: Sreedev Kodichat
Author-email: sreedevpadmakumar@gmail.com
License: MIT
Keywords: Python Random Image Generator Perlin Noise Algorithm
Platform: UNKNOWN
Requires-Dist: matplotlib
Requires-Dist: numpy
